counter.v
module counter (
    input clk,
    input reset,
    input enable,
    output reg [3:0] count
);
    always @(posedge clk or posedge reset) begin
        if (reset)
            count <= 4'b0000;
        else if (enable)
            count <= count + 1;
    end
endmodule

counter_tb.v
module testbench;
    reg clk, reset, enable;
    wire [3:0] count;

    // Test edilen modül bağlanıyor
    counter uut (
        .clk(clk),
        .reset(reset),
        .enable(enable),
        .count(count)
    );

    // Saat sinyali üretimi
    always #5 clk = ~clk; // Clock her 5 birimde bir değişir

    initial begin
        $dumpfile("counter.vcd"); // VCD dosyasını oluştur
        $dumpvars(0, clk, reset, enable, count); // Tüm sinyalleri kaydet

        // Test durumları
        clk = 0; reset = 1; enable = 0; #10;  // Reset aktif, sayaç sıfırlanır
        reset = 0; enable = 1; #50;          // Sayaç artar
        enable = 0; #30;                     // Sayaç durur
        enable = 1; #40;                     // Sayaç tekrar artar
        $finish;                             // Simülasyonu sonlandır
    end
endmodule

counter.vcd
$date
	Fri Nov 29 22:32:24 2024
$end
$version
	Icarus Verilog
$end
$timescale
	1s
$end
$scope module testbench $end
$var reg 1 ! clk $end
$upscope $end
$scope module testbench $end
$var reg 1 " reset $end
$upscope $end
$scope module testbench $end
$var reg 1 # enable $end
$upscope $end
$scope module testbench $end
$var wire 4 $ count [3:0] $end
$upscope $end
$enddefinitions $end
$comment Show the parameter values. $end
$dumpall
$end
#0
$dumpvars
b0 $
0#
1"
0!
$end
#5
1!
#10
0!
1#
0"
#15
b1 $
1!
#20
0!
#25
b10 $
1!
#30
0!
#35
b11 $
1!
#40
0!
#45
b100 $
1!
#50
0!
#55
b101 $
1!
#60
0!
0#
#65
1!
#70
0!
#75
1!
#80
0!
#85
1!
#90
0!
1#
#95
b110 $
1!
#100
0!
#105
b111 $
1!
#110
0!
#115
b1000 $
1!
#120
0!
#125
b1001 $
1!
