decoder.v
module decoder (
    input wire [3:0] in,    // 4-bit giriş
    input wire enable,      // Enable sinyali
    output reg [15:0] out   // 16-bit çıkış
);

    always @(*) begin
        if (enable) begin
            out = 16'b0;          // Tüm çıkışları sıfırla
            out[in] = 1'b1;       // Giriş adresine karşılık gelen çıkışı 1 yap
        end else begin
            out = 16'b0;          // Enable düşükse tüm çıkışlar sıfır
        end
    end
endmodule

counter.v
module counter (
    input clk,
    input reset,
    input enable,
    output reg [3:0] count
);
    always @(posedge clk or posedge reset) begin
        if (reset)
            count <= 4'b0000;
        else if (enable)
            count <= count + 1;
    end
endmodule

mux2to1.v
module mux2to1(
    input wire a,     // Giriş 1
    input wire b,     // Giriş 2
    input wire sel,   // Seçim sinyali
    output wire y     // Çıkış
);

    assign y = (sel) ? b : a; // Seçim mantığı

endmodule

alu.v
module ALU (
    input [31:0] a,       // 32-bit giriş 1
    input [31:0] b,       // 32-bit giriş 2
    input [1:0] opcode,   // İşlem kodu (00: +, 01: -, 10: *, 11: /)
    output reg [31:0] result, // Sonuç
    output reg ready          // Hazır sinyali
);

    always @(*) begin
        ready = 1; // İşlem sonucunun hazır olduğunu belirtir
        case (opcode)
            2'b00: result = a + b; // Toplama
            2'b01: result = a - b; // Çıkarma
            2'b10: result = a * b; // Çarpma
            2'b11: result = b != 0 ? a / b : 32'hx; // Bölme (sıfıra bölme kontrolü)
            default: result = 32'hx; // Geçersiz işlem
        endcase
    end

endmodule

integrated_testbench.v
`timescale 1ns/1ps

module integrated_testbench;

  // Ortak sinyallerin tanımlanması
  reg clk;
  reg reset;
  reg enable;
  reg [3:0] alu_a, alu_b;
  reg [1:0] alu_op;
  wire [7:0] alu_result;
  reg mux_select;
  reg [3:0] mux_in0, mux_in1;
  wire [3:0] mux_out;
  wire [3:0] counter_out;
  reg [3:0] decoder_input;
  wire [15:0] decoder_output;

  // Saat sinyali üretimi
  initial begin
    clk = 0;
    forever #5 clk = ~clk; // 10 ns period
  end

  // Modül örnekleri
  ALU alu_inst (
    .a({28'b0, alu_a}), // 32-bit genişlik için sıfır ile doldur
    .b({28'b0, alu_b}),
    .opcode({1'b0, alu_opcode}), // 2-bit genişlik için sıfır ile doldur
    .result(alu_result),
    .ready(alu_ready)
);


  mux2to1 mux_inst (
    .a(mux_in0[0]), // Eğer sadece 1-bit kullanıyorsanız
    .b(mux_in1[0]),
    .sel(mux_sel),
    .y(mux_out[0])
);


  counter counter_inst (
    .clk(clk),
    .reset(reset),
    .enable(enable),
    .count(counter_out)
  );

  decoder decoder_inst (
    .in(decoder_input),
    .out(decoder_output)
  );

  // Test senaryoları
  initial begin
    $dumpfile("integrated_testbench.vcd"); // Dalgaform dosyasını tanımla
    $dumpvars(0, integrated_testbench);    // Tüm sinyalleri kaydet
    
    // Başlangıç değerleri
    reset = 1; enable = 0;
    alu_a = 4'b0000; alu_b = 4'b0000; alu_op = 2'b00;
    mux_in0 = 4'b0000; mux_in1 = 4'b1111; mux_select = 0;
    decoder_input = 4'b0000;

    // Reset işlemi
    #10 reset = 0; enable = 1;

    // ALU işlemi test
    #10 alu_a = 4'b0101; alu_b = 4'b0011; alu_op = 2'b00; // Toplama
    #10 alu_op = 2'b01; // Çıkarma
    #10 alu_op = 2'b10; // Çarpma (destekliyorsa)

    // MUX işlemi test
    #10 mux_select = 1;

    // Counter işlemi test
    #50 reset = 1; #10 reset = 0; // Reset sonrası sayma

    // Decoder işlemi test
    #10 decoder_input = 4'b0010;
    #10 decoder_input = 4'b0100;

    // Simülasyonu sonlandır
    #100 $finish;
end


endmodule

integrated_testbench.vcd
$date
	Wed Dec 25 15:26:11 2024
$end
$version
	Icarus Verilog
$end
$timescale
	1ps
$end
$scope module integrated_testbench $end
$var wire 1 ! mux_sel $end
$var wire 4 " mux_out [3:0] $end
$var wire 16 # decoder_output [15:0] $end
$var wire 4 $ counter_out [3:0] $end
$var wire 8 % alu_result [7:0] $end
$var wire 1 & alu_ready $end
$var reg 4 ' alu_a [3:0] $end
$var reg 4 ( alu_b [3:0] $end
$var reg 2 ) alu_op [1:0] $end
$var reg 1 * clk $end
$var reg 4 + decoder_input [3:0] $end
$var reg 1 , enable $end
$var reg 4 - mux_in0 [3:0] $end
$var reg 4 . mux_in1 [3:0] $end
$var reg 1 / mux_select $end
$var reg 1 0 reset $end
$scope module alu_inst $end
$var wire 32 1 a [31:0] $end
$var wire 32 2 b [31:0] $end
$var wire 2 3 opcode [1:0] $end
$var reg 1 & ready $end
$var reg 32 4 result [31:0] $end
$upscope $end
$scope module counter_inst $end
$var wire 1 * clk $end
$var wire 1 , enable $end
$var wire 1 0 reset $end
$var reg 4 5 count [3:0] $end
$upscope $end
$scope module decoder_inst $end
$var wire 1 6 enable $end
$var wire 4 7 in [3:0] $end
$var reg 16 8 out [15:0] $end
$upscope $end
$scope module mux_inst $end
$var wire 1 9 a $end
$var wire 1 : b $end
$var wire 1 ! sel $end
$var wire 1 ; y $end
$upscope $end
$upscope $end
$enddefinitions $end
$comment Show the parameter values. $end
$dumpall
$end
#0
$dumpvars
x;
1:
09
b0 8
b0 7
z6
b0 5
bx 4
b0z 3
b0 2
b0 1
10
0/
b1111 .
b0 -
0,
b0 +
0*
b0 )
b0 (
b0 '
1&
bx %
b0 $
b0 #
bzx "
z!
$end
#5000
1*
#10000
0*
1,
00
#15000
b1 $
b1 5
1*
#20000
0*
b11 2
b11 (
b101 1
b101 '
#25000
b10 $
b10 5
1*
#30000
0*
b1 )
#35000
b11 $
b11 5
1*
#40000
0*
b10 )
#45000
b100 $
b100 5
1*
#50000
0*
1/
#55000
b101 $
b101 5
1*
#60000
0*
#65000
b110 $
b110 5
1*
#70000
0*
#75000
b111 $
b111 5
1*
#80000
0*
#85000
b1000 $
b1000 5
1*
#90000
0*
#95000
b1001 $
b1001 5
1*
#100000
b0 $
b0 5
0*
10
#105000
1*
#110000
0*
00
#115000
b1 $
b1 5
1*
#120000
0*
b10 +
b10 7
#125000
b10 $
b10 5
1*
#130000
0*
b100 +
b100 7
#135000
b11 $
b11 5
1*
#140000
0*
#145000
b100 $
b100 5
1*
#150000
0*
#155000
b101 $
b101 5
1*
#160000
0*
#165000
b110 $
b110 5
1*
#170000
0*
#175000
b111 $
b111 5
1*
#180000
0*
#185000
b1000 $
b1000 5
1*
#190000
0*
#195000
b1001 $
b1001 5
1*
#200000
0*
#205000
b1010 $
b1010 5
1*
#210000
0*
#215000
b1011 $
b1011 5
1*
#220000
0*
#225000
b1100 $
b1100 5
1*
