generated_module.v

module counter (
    input clk,
    input reset,
    input enable,
    output reg [3:0] count
);
    always @(posedge clk or posedge reset) begin
        if (reset)
            count <= 4'b0000;
        else if (enable)
            count <= count + 1;
    end
endmodule

testbench.v
module testbench;
    reg clk, reset, enable; // Girişler
    wire [3:0] count;       // Çıkışlar

    // Test edilecek modülü bağla
    counter uut (
        .clk(clk),
        .reset(reset),
        .enable(enable),
        .count(count)
    );

    // Test senaryoları
    initial begin
        $dumpfile("testbench.vcd"); // Dalga formu dosyası
        $dumpvars(0, testbench);    // Tüm değişkenleri kaydet

        // Test başlangıcı
        clk = 0; reset = 1; enable = 0; #10; // Reset durumu
        reset = 0; enable = 1; #50;         // Enable aktifken sayaç
        enable = 0; #50;                    // Enable kapalıyken sayaç durur
        $finish;                            // Testi bitir
    end

    // Saat sinyali üretimi
    always #5 clk = ~clk;
endmodule

testbench.vcd
$date
	Wed Nov 27 19:50:46 2024
$end
$version
	Icarus Verilog
$end
$timescale
	1s
$end
$scope module testbench $end
$var wire 4 ! count [3:0] $end
$var reg 1 " clk $end
$var reg 1 # enable $end
$var reg 1 $ reset $end
$scope module uut $end
$var wire 1 " clk $end
$var wire 1 # enable $end
$var wire 1 $ reset $end
$var reg 4 % count [3:0] $end
$upscope $end
$upscope $end
$enddefinitions $end
$comment Show the parameter values. $end
$dumpall
$end
#0
$dumpvars
b0 %
1$
0#
0"
b0 !
$end
#5
1"
#10
0"
1#
0$
#15
b1 !
b1 %
1"
#20
0"
#25
b10 !
b10 %
1"
#30
0"
#35
b11 !
b11 %
1"
#40
0"
#45
b100 !
b100 %
1"
#50
0"
#55
b101 !
b101 %
1"
#60
0"
0#
